part1.v
`timescale 1ns/1ps

module dFF(
    input D, clk, reset,
    output reg Q
);
    always @(posedge clk) begin
        if(~reset) begin
            Q<=0;
        end
        else
            Q <=D;
    end
endmodule

module mooreSM(
    input in, clk, reset, 
    output [2:0] out
);

    wire out0,out2;

    wire ps0,ps1, ps0_bar, ps1_bar, in_bar;
    wire ns0,ns1;
    wire top_ns0,bot_ns0, top_ns1, bot_ns1;

    not(ps0_bar,ps0);
    not(ps1_bar,ps1);
    not(in_bar,in);

    and(top_ns1, ps1,in_bar);
    and(bot_ns1, in, ps0);
    or(ns1,top_ns1,bot_ns1);

    xor(top_ns0,in,ps0);
    and(bot_ns0,in,ps1_bar);
    or(ns0,top_ns0,bot_ns0);

    dFF d0(ns0,clk,reset,ps0);
    dFF d1(ns1,clk,reset,ps1);
    
    and(out[2],ps1,ps0_bar);
    assign out[1] = ps0;
    assign out[0] = ~(ps0 ^ ps1);

endmodule

tb1.v
`timescale 1ns/1ps

module mooreTb;

    reg in, clk, reset;
    wire [2:0] out;
    integer i,j;

    mooreSM dat(.in(in),.clk(clk),.reset(reset),.out(out));

    initial begin
        $dumpfile("wave1.vcd");
        $dumpvars(0, mooreTb);

        clk = 1;
        reset = 0;
        in = 1;
        #1 reset = 1;
        for(i=0; i<50;i=i+1) begin
            #10 clk = ~clk;
        end
    end
    initial begin
        #15 in = 0;
        #50 in = 1;
        #100 reset = 0;
        #50 reset = 1;
        #100 in = 0;
        #50 in = 1;
    end

    always @(out,reset,in)
        $monitor("state:%d\t\tin: %d     reset: %d",out,in,reset);
endmodule

wave1.vcd
$date
	Fri May 10 19:44:07 2024
$end
$version
	Icarus Verilog
$end
$timescale
	1ps
$end
$scope module mooreTb $end
$var wire 3 ! out [2:0] $end
$var reg 1 " clk $end
$var reg 1 # in $end
$var reg 1 $ reset $end
$var integer 32 % i [31:0] $end
$scope module dat $end
$var wire 1 & bot_ns0 $end
$var wire 1 ' bot_ns1 $end
$var wire 1 " clk $end
$var wire 1 # in $end
$var wire 1 ( in_bar $end
$var wire 1 ) ns0 $end
$var wire 1 * ns1 $end
$var wire 1 + ps0_bar $end
$var wire 1 , ps1_bar $end
$var wire 1 $ reset $end
$var wire 1 - top_ns0 $end
$var wire 1 . top_ns1 $end
$var wire 1 / ps1 $end
$var wire 1 0 ps0 $end
$var wire 3 1 out [2:0] $end
$scope module d0 $end
$var wire 1 ) D $end
$var wire 1 " clk $end
$var wire 1 $ reset $end
$var reg 1 0 Q $end
$upscope $end
$scope module d1 $end
$var wire 1 * D $end
$var wire 1 " clk $end
$var wire 1 $ reset $end
$var reg 1 / Q $end
$upscope $end
$upscope $end
$upscope $end
$enddefinitions $end
$comment Show the parameter values. $end
$dumpall
$end
#0
$dumpvars
b1 1
00
0/
0.
1-
1,
1+
0*
1)
0(
0'
1&
bx %
0$
1#
1"
b1 !
$end
#1000
b0 %
1$
#11000
b1 %
0"
#15000
0)
1(
0-
0&
0#
#21000
b10 %
1"
#31000
b11 %
0"
#41000
b100 %
1"
#51000
b101 %
0"
#61000
b110 %
1"
#65000
1)
0(
1-
1&
1#
#71000
b111 %
0"
#81000
1*
0-
1'
0+
b10 !
b10 1
10
b1000 %
1"
#91000
b1001 %
0"
#101000
0)
b11 !
b11 1
0&
0,
1/
b1010 %
1"
#111000
b1011 %
0"
#121000
1)
0*
1-
0'
1+
b100 !
b100 1
00
b1100 %
1"
#131000
b1101 %
0"
#141000
1&
1)
1*
1,
0-
1'
0+
0/
b10 !
b10 1
10
b1110 %
1"
#151000
b1111 %
0"
#161000
0)
b11 !
b11 1
0&
0,
1/
b10000 %
1"
#165000
0$
#171000
b10001 %
0"
#181000
1&
1)
0*
1,
1-
0'
1+
0/
b1 !
b1 1
00
b10010 %
1"
#191000
b10011 %
0"
#201000
b10100 %
1"
#211000
b10101 %
0"
#215000
1$
#221000
1*
0-
1'
0+
b10 !
b10 1
10
b10110 %
1"
#231000
b10111 %
0"
#241000
0)
b11 !
b11 1
0&
0,
1/
b11000 %
1"
#251000
b11001 %
0"
#261000
1)
0*
1-
0'
1+
b100 !
b100 1
00
b11010 %
1"
#271000
b11011 %
0"
#281000
1*
1&
0-
1'
0+
1,
b10 !
b10 1
10
0/
b11100 %
1"
#291000
b11101 %
0"
#301000
0)
b11 !
b11 1
0&
0,
1/
b11110 %
1"
#311000
b11111 %
0"
#315000
1.
1*
1)
1(
0'
1-
0#
#321000
b100000 %
1"
#331000
b100001 %
0"
#341000
b100010 %
1"
#351000
b100011 %
0"
#361000
b100100 %
1"
#365000
0.
0)
0(
1'
0-
1#
#371000
b100101 %
0"
#381000
1)
0*
1-
0'
1+
b100 !
b100 1
00
b100110 %
1"
#391000
b100111 %
0"
#401000
1*
1&
0-
1'
0+
1,
b10 !
b10 1
10
0/
b101000 %
1"
#411000
b101001 %
0"
#421000
0)
b11 !
b11 1
0&
0,
1/
b101010 %
1"
#431000
b101011 %
0"
#441000
1)
0*
1-
0'
1+
b100 !
b100 1
00
b101100 %
1"
#451000
b101101 %
0"
#461000
1&
1)
1*
1,
0-
1'
0+
0/
b10 !
b10 1
10
b101110 %
1"
#471000
b101111 %
0"
#481000
0)
b11 !
b11 1
0&
0,
1/
b110000 %
1"
#491000
b110001 %
0"
#501000
1)
0*
1-
0'
1+
b100 !
b100 1
00
b110010 %
1"
