2.v
`timescale 1ns/1ps

module counterDecoder(
    input stop, clk,
    output out, 
    output [3:0] countOut
);

    reg [3:0] ps = 4'd0;
    wire [3:0] ns, inc;

    always @(posedge clk)
        ps <= ns;

    assign inc = ps+1;

    assign ns = stop ? ps : (ps == 7) ? 0 :inc;

    assign countOut = ps;
    assign out = (ps == 2) ? 1:0;

endmodule

2tb.v
`timescale 1ns/1ps

module countDecodeTb;

    reg stop, clk;
    wire out;
    wire [3:0] countOut;
    integer i,j;

    counterDecoder dat(.stop(stop),.clk(clk),.out(out), .countOut(countOut));

    initial begin
        $dumpfile("wave2.vcd");
        $dumpvars(0, countDecodeTb);

        clk = 0;
        for(i=0; i<50;i=i+1) begin
            #10 clk = ~clk;
        end
    end
    initial begin
        stop = 0;
        #75 stop = 1;
        #40 stop = 0;
        #120 stop = 1;
        #70 stop = 0;
    end

    always @(out,stop) begin
        $monitor("state:%d\t\tout:%d\tstop: %d",countOut,out,stop);
    end

endmodule

wave2.vcd
$date
	Fri May 10 21:49:35 2024
$end
$version
	Icarus Verilog
$end
$timescale
	1ps
$end
$scope module countDecodeTb $end
$var wire 1 ! out $end
$var wire 4 " countOut [3:0] $end
$var reg 1 # clk $end
$var reg 1 $ stop $end
$var integer 32 % i [31:0] $end
$scope module dat $end
$var wire 1 # clk $end
$var wire 4 & countOut [3:0] $end
$var wire 1 $ stop $end
$var wire 1 ! out $end
$var wire 4 ' ns [3:0] $end
$var wire 4 ( inc [3:0] $end
$var reg 4 ) ps [3:0] $end
$upscope $end
$upscope $end
$enddefinitions $end
$comment Show the parameter values. $end
$dumpall
$end
#0
$dumpvars
b0 )
b1 (
b1 '
b0 &
b0 %
0$
0#
b0 "
0!
$end
#10000
b10 '
b10 (
b1 "
b1 &
b1 )
b1 %
1#
#20000
b10 %
0#
#30000
b11 '
1!
b11 (
b10 "
b10 &
b10 )
b11 %
1#
#40000
b100 %
0#
#50000
b100 '
0!
b100 (
b11 "
b11 &
b11 )
b101 %
1#
#60000
b110 %
0#
#70000
b101 '
b101 (
b100 "
b100 &
b100 )
b111 %
1#
#75000
b100 '
1$
#80000
b1000 %
0#
#90000
b1001 %
1#
#100000
b1010 %
0#
#110000
b1011 %
1#
#115000
b101 '
0$
#120000
b1100 %
0#
#130000
b110 '
b110 (
b101 "
b101 &
b101 )
b1101 %
1#
#140000
b1110 %
0#
#150000
b111 '
b111 (
b110 "
b110 &
b110 )
b1111 %
1#
#160000
b10000 %
0#
#170000
b0 '
b1000 (
b111 "
b111 &
b111 )
b10001 %
1#
#180000
b10010 %
0#
#190000
b1 '
b1 (
b0 "
b0 &
b0 )
b10011 %
1#
#200000
b10100 %
0#
#210000
b10 '
b10 (
b1 "
b1 &
b1 )
b10101 %
1#
#220000
b10110 %
0#
#230000
b11 '
1!
b11 (
b10 "
b10 &
b10 )
b10111 %
1#
#235000
b10 '
1$
#240000
b11000 %
0#
#250000
b11001 %
1#
#260000
b11010 %
0#
#270000
b11011 %
1#
#280000
b11100 %
0#
#290000
b11101 %
1#
#300000
b11110 %
0#
#305000
b11 '
0$
#310000
b100 '
0!
b100 (
b11 "
b11 &
b11 )
b11111 %
1#
#320000
b100000 %
0#
#330000
b101 '
b101 (
b100 "
b100 &
b100 )
b100001 %
1#
#340000
b100010 %
0#
#350000
b110 '
b110 (
b101 "
b101 &
b101 )
b100011 %
1#
#360000
b100100 %
0#
#370000
b111 '
b111 (
b110 "
b110 &
b110 )
b100101 %
1#
#380000
b100110 %
0#
#390000
b0 '
b1000 (
b111 "
b111 &
b111 )
b100111 %
1#
#400000
b101000 %
0#
#410000
b1 '
b1 (
b0 "
b0 &
b0 )
b101001 %
1#
#420000
b101010 %
0#
#430000
b10 '
b10 (
b1 "
b1 &
b1 )
b101011 %
1#
#440000
b101100 %
0#
#450000
b11 '
1!
b11 (
b10 "
b10 &
b10 )
b101101 %
1#
#460000
b101110 %
0#
#470000
b100 '
0!
b100 (
b11 "
b11 &
b11 )
b101111 %
1#
#480000
b110000 %
0#
#490000
b101 '
b101 (
b100 "
b100 &
b100 )
b110001 %
1#
#500000
b110010 %
0#
